sunkit_pyvista/__init__.py
sunkit_pyvista/_version.py
sunkit_pyvista/conftest.py
sunkit_pyvista/plotter.py
sunkit_pyvista/sample.py
sunkit_pyvista/utils.py
sunkit_pyvista/tests/__init__.py
sunkit_pyvista/tests/conftest.py
sunkit_pyvista/tests/test_magex.py
sunkit_pyvista/tests/test_plotting.py
sunkit_pyvista/tests/test_pyvista.py
sunkit_pyvista/tests/image_cache/field_lines_figure.png
sunkit_pyvista/tests/image_cache/plot_map_with_functionality.png
sunkit_pyvista-0.3.0.dist-info/METADATA
sunkit_pyvista-0.3.0.dist-info/WHEEL
sunkit_pyvista-0.3.0.dist-info/top_level.txt
sunkit_pyvista-0.3.0.dist-info/RECORD
