Metadata-Version: 2.1
Name: sunkit_pyvista
Version: 0.3.0
Summary: 3D visualisation of solar physics data with pyvista.
Author-email: The SunPy Community <sunpy@googlegroups.com>
Project-URL: changelog, https://docs.sunpy.org/projects/sunkit-magex/en/stable/changelog
Project-URL: documentation, https://docs.sunpy.org/projects/sunkit-magex/en/stable/
Project-URL: homepage, https://sunpy.org/
Project-URL: issue_tracker, https://github.com/sunpy/sunkit-pyvista/issues
Project-URL: repository, https://github.com/sunpy/sunkit-pyvista
Keywords: solar physics,solar,science,3d,plotting,visualisation
Platform: any
Classifier: Development Status :: 3 - Alpha
Classifier: Intended Audience :: Science/Research
Classifier: License :: OSI Approved :: BSD License
Classifier: Natural Language :: English
Classifier: Operating System :: OS Independent
Classifier: Programming Language :: Python
Classifier: Programming Language :: Python :: 3
Classifier: Programming Language :: Python :: 3.10
Classifier: Programming Language :: Python :: 3.11
Classifier: Programming Language :: Python :: 3.12
Classifier: Topic :: Scientific/Engineering :: Visualization
Provides: sunkit_pyvista
Requires-Python: >=3.10
Requires-Dist: pyvista[all] >=0.43.9
Requires-Dist: sunpy[map] >=5.0.0
Provides-Extra: all
Requires-Dist: sunkit-pyvista ; extra == 'all'
Provides-Extra: dev
Requires-Dist: sunkit-pyvista[docs,tests] ; extra == 'dev'
Provides-Extra: docs
Requires-Dist: sunkit-pyvista[all] ; extra == 'docs'
Requires-Dist: sphinx-automodapi ; extra == 'docs'
Requires-Dist: sphinx-changelog ; extra == 'docs'
Requires-Dist: sphinx-design ; extra == 'docs'
Requires-Dist: sphinx-gallery ; extra == 'docs'
Requires-Dist: sphinx ; extra == 'docs'
Requires-Dist: sunkit-magex ; extra == 'docs'
Requires-Dist: sunpy-sphinx-theme ; extra == 'docs'
Requires-Dist: streamtracer ; extra == 'docs'
Provides-Extra: tests
Requires-Dist: sunkit-pyvista[all] ; extra == 'tests'
Requires-Dist: pytest-astropy ; extra == 'tests'
Requires-Dist: scikit-image ; extra == 'tests'
Requires-Dist: streamtracer ; extra == 'tests'
Requires-Dist: sunkit-magex ; extra == 'tests'
